<?xml version="1.0" encoding="UTF-8"?>
<chefkochbuch xmlns:xsi="http://www.w3.org/2001/XMLSchema-instance"
    xsi:noNamespaceSchemaLocation="file:/C:/Users/Ngoc-Anh/Dropbox/FH/4.%20Semester/WBA2/Phase1/aufgabe3d_chefkochbuch_schema-kommentare.xsd">
    <rezept id="2" name="Salamibrötchen" portionen="1">
        <zutaten>
            <zutat menge="1" einheit="Stk." name="Brötchen"/>
            <zutat menge="1" einheit="Scheibe" name="Salami"/>
        </zutaten>
        <schritte>
            <schritt>Brötchen aufschneiden.</schritt>
            <schritt>Salami reinlegen.</schritt>
        </schritte>
    </rezept>
</chefkochbuch>